eb_sqs_worker/__init__.py
eb_sqs_worker/admin.py
eb_sqs_worker/apps.py
eb_sqs_worker/decorators.py
eb_sqs_worker/models.py
eb_sqs_worker/sqs.py
eb_sqs_worker/tasks.py
eb_sqs_worker/tests.py
eb_sqs_worker/urls.py
eb_sqs_worker/views.py
eb_sqs_worker/migrations/__init__.py
django_eb_sqs_worker-0.5.0.dist-info/LICENSE
django_eb_sqs_worker-0.5.0.dist-info/METADATA
django_eb_sqs_worker-0.5.0.dist-info/WHEEL
django_eb_sqs_worker-0.5.0.dist-info/top_level.txt
django_eb_sqs_worker-0.5.0.dist-info/RECORD
