Metadata-Version: 2.1
Name: django-eb-sqs-worker
Version: 0.5.0
Summary: Django Background Tasks for Amazon Elastic Beanstalk
Home-page: https://github.com/DataGreed/django-eb-sqs-worker/
Author: Alexey Strelkov
Author-email: datagreed@gmail.com
License: UNKNOWN
Platform: UNKNOWN
Classifier: Programming Language :: Python :: 3
Classifier: License :: OSI Approved :: MIT License
Classifier: Operating System :: OS Independent
Requires-Python: >=3.6
Requires-Dist: boto3 (>=1.10.28)
Requires-Dist: botocore (>=1.17.5)
Requires-Dist: Django (>=2.2)
Requires-Dist: docutils (>=0.15.2)
Requires-Dist: jmespath (>=0.10.0)
Requires-Dist: python-dateutil (>=2.8.1)
Requires-Dist: pytz (>=2020.1)
Requires-Dist: s3transfer (>=0.3.3)
Requires-Dist: six (>=1.15.0)
Requires-Dist: urllib3 (>=1.25.9)
